{
  "query": "What is the internal codename for the 2027 HelixCode release?",
  "qkey": "q1",
  "ranked": [
    {
      "id": "doc_codename",
      "text": "The internal codename for the 2027 HelixCode release is Borealis-9.",
      "score": 0.885177716460242
    },
    {
      "id": "doc_ci",
      "text": "The HelixCode continuous integration pipeline runs unit tests before every merge to main.",
      "score": 0.7166139003402228
    },
    {
      "id": "doc_sidecar",
      "text": "The internal service-mesh sidecar used internally for HelixLLM routing is called Quillfeather-7.",
      "score": 0.6766061971219052
    },
    {
      "id": "doc_coffee",
      "text": "Coffee brewing techniques improve flavor extraction using controlled water temperature.",
      "score": 0.45773165497504925
    },
    {
      "id": "doc_revenue",
      "text": "Quarterly revenue rose four percent.",
      "score": 0.3922136640424146
    },
    {
      "id": "doc_cat",
      "text": "The cat sat on the mat.",
      "score": 0.30288582666596114
    }
  ]
}